BitBooleanFlags.py
__init__.py
example.py
bit_boolean_flags-2.0.dist-info/LICENSE.txt
bit_boolean_flags-2.0.dist-info/METADATA
bit_boolean_flags-2.0.dist-info/WHEEL
bit_boolean_flags-2.0.dist-info/top_level.txt
bit_boolean_flags-2.0.dist-info/RECORD
