Metadata-Version: 2.1
Name: bit-boolean-flags
Version: 2.0
Summary: Bit boolean flag wrapper, allows you to store flags inside a single number.
Home-page: https://github.com/redocnib/BitBooleanFlags
Author: Kiran AK
Author-email: kiran.txt@gmail.com
License: MIT
Download-URL: https://github.com/redocnib/BitBooleanFlags/archive/v1.0.tar.gz
Keywords: bit flags,boolean bit flags
Platform: Cross platform
Classifier: Intended Audience :: Developers
Classifier: Programming Language :: Python :: 2
Classifier: Programming Language :: Python :: 3
License-File: LICENSE.txt
